{"town":"新化區","city":"臺南市","store":[{"address":"臺南市新化區北勢里中正路１２０７號","code":"5905060054","name":"全家康藥師藥局","tel":"06-5980866"},{"address":"臺南市新化區護國里中山路１８５號","code":"5905060081","name":"新化景惠藥局","tel":"06-5909659"},{"address":"臺南市新化區忠孝路２８１號","code":"5905060090","name":"加賀藥局","tel":"06-5983865"},{"address":"臺南市新化區中山路５０７號","code":"5905060107","name":"新化健保藥局","tel":"06-5983328"},{"address":"臺南市新化區中山路４８７號１樓","code":"5905060116","name":"美華健保藥局","tel":"06-5907859"},{"address":"臺南市新化區護國里中山路１５０－１號１樓","code":"5905060125","name":"美麗安藥局","tel":"06-5909509"},{"address":"臺南市新化區忠孝路１１８號１樓","code":"5905060134","name":"得安藥局","tel":"06-5981333"},{"address":"臺南市新化區護國里中山路２３２號","code":"5905060143","name":"來德藥局","tel":"06-5800193"},{"address":"臺南市新化區清水里中山路４２０號１樓","code":"5905060161","name":"和德藥局新化店","tel":"06-5802518"},{"address":"臺南市新化區觀音里中正路５４５號","code":"5941060014","name":"富傑藥局","tel":"06-5907185"},{"address":"台南市新化區那拔里２９０號","code":"5941060050","name":"炳騰藥局","tel":"06-5911687"},{"address":"臺南市新化區護國里中正路４０４號","code":"5941061146","name":"欣華藥局","tel":"06-5908832"},{"address":"臺南市新化區武安里信義路３２０號","code":"5941061173","name":"杏安藥局","tel":"06-5801081"},{"address":"臺南市新化區中正路５２８號","code":"5941061299","name":"元一藥師藥局","tel":"06-5980795"},{"address":"臺南市新化區中山路４２４號１樓","code":"5941061306","name":"千福藥局","tel":"06-5905862"},{"address":"臺南市新化區忠孝路１１６之３號","code":"5941061342","name":"安麗兒藥局新化店","tel":"06-5986029"},{"address":"臺南市新化區健康路十三鄰１４３號","code":"2341060019","name":"臺南市新化區衛生所","tel":"06-5905398"}]}