{"city": "雲林縣", "town": "土庫鎮", "store": [{"name": "健康藥局", "address": "雲林縣土庫鎮順天里中正路１１號", "tel": "(05)6622889", "code": "5939050044"}, {"name": "常春藤藥局", "address": "雲林縣土庫鎮忠正里中山路２４６號", "tel": "(05)6627371", "code": "5939050124"}, {"name": "土庫台丞藥局", "address": "雲林縣土庫鎮中正路１１２號", "tel": "(05)6626677", "code": "5939051185"}, {"name": "祥安藥局", "address": "雲林縣土庫鎮東平里馬光路３８－１號", "tel": "(05)6656610", "code": "5939051229"}, {"name": "祐安藥局", "address": "雲林縣土庫鎮馬光路３９－１號", "tel": "(05)6655938", "code": "5939051247"}, {"name": "義泰藥局", "address": "雲林縣土庫鎮宮北里中正路２０２號", "tel": "(05)6624778", "code": "5939050071"}, {"name": "友杏健康健保藥局", "address": "雲林縣土庫鎮北平里民權路１４號", "tel": "(05)6651758", "code": "5939051194"}, {"name": "大方藥局", "address": "雲林縣土庫鎮中正路１０６號", "tel": "(05)6629199", "code": "5939051176"}, {"name": "天愛藥局", "address": "雲林縣土庫鎮中山路８０號", "tel": "(05)6629923", "code": "5939051238"}]}