{"city": "澎湖縣", "town": "馬公市", "store": [{"name": "大智藥局", "address": "澎湖縣馬公市陽明里大智街２６號", "tel": "06-9262151", "code": "5944010025"}, {"name": "新見安藥局", "address": "澎湖縣馬公市光明里光復路９５號", "tel": "06-9277346", "code": "5944010043"}, {"name": "敏松藥局", "address": "澎湖縣馬公市民生路２５－９號", "tel": "06-9273241", "code": "5944010061"}, {"name": "合珍藥局", "address": "為澎湖縣馬公市鎖港里３８７－１號", "tel": "06-9953082", "code": "5944010070"}, {"name": "宏安藥局", "address": "澎湖縣馬公市中華路５４號", "tel": "06-9273048", "code": "5944010089"}, {"name": "益立康藥局", "address": "澎湖縣馬公市中華路２９３號", "tel": "06-9271017", "code": "5944011326"}, {"name": "振發藥局", "address": "澎湖縣馬公市中華路１９７號", "tel": "06-9274529", "code": "5944011335"}, {"name": "信成藥局", "address": "澎湖縣馬公市中華路８２－２號", "tel": "06-9276137", "code": "5944011353"}, {"name": "永安藥局", "address": "澎湖縣馬公市陽明路１１２號", "tel": "06-9265317", "code": "5944011371"}, {"name": "陽明金福藥局", "address": "澎湖縣馬公市陽明路５０號", "tel": "06-9260855", "code": "5944011406"}, {"name": "宏淇藥局", "address": "澎湖縣馬公市大勇街５０號", "tel": "06-9260782", "code": "5944011424"}, {"name": "東文藥局", "address": "澎湖縣馬公市東文里文山路６６號", "tel": "06-9221433", "code": "5944011433"}, {"name": "澎躍藥局", "address": "澎湖縣馬公市朝陽里文昌街５０－５號６樓", "tel": "06-9277343", "code": "5944011442"}, {"name": "澎湖縣馬公市第三衛生所", "address": "澎湖縣馬公市西文里１１８之２號", "tel": "06-9211723", "code": "2344011036"}]}